crawl4us.py
crawl4us-0.1.3.dist-info/DESCRIPTION.rst
crawl4us-0.1.3.dist-info/METADATA
crawl4us-0.1.3.dist-info/RECORD
crawl4us-0.1.3.dist-info/WHEEL
crawl4us-0.1.3.dist-info/metadata.json
crawl4us-0.1.3.dist-info/top_level.txt
