Metadata-Version: 2.0
Name: crawl4us
Version: 0.1.3
Summary: A Python web crawler looking wildly for tables
Home-page: https://github.com/camilamaia/crawl4us
Author: Camila Maia
Author-email: UNKNOWN
License: UNKNOWN
Project-URL: Bug Reports, https://github.com/camilamaia/crawl4us/issues
Project-URL: Source, https://github.com/camilamaia/crawl4us
Keywords: sample setuptools development web scraping crawler
Platform: UNKNOWN
Classifier: Development Status :: 3 - Alpha
Classifier: Intended Audience :: Developers
Classifier: Topic :: Software Development :: Build Tools
Classifier: License :: OSI Approved :: MIT License
Classifier: Programming Language :: Python :: 3.6
Requires-Dist: beautifulsoup4
Requires-Dist: requests
Requires-Dist: pandas
Provides-Extra: dev
Requires-Dist: pylint; extra == 'dev'
Provides-Extra: test
Requires-Dist: pytest; extra == 'test'
